{
  "authorizationFile": "./src/assets/authorization-tags.json",
  "baseName": "CS-BASIC",
  "chargePointModel": "Simulator simple",
  "chargePointVendor": "Ovomaltin",
  "power": 75000,
  "powerUnit": "W",
  "numberOfConnectors": 3,
  "randomConnectors": false,
  "Configuration": {
    "configurationKey": [
      {
        "key": "NumberOfConnectors",
        "readonly": true,
        "value": 3
      },
      {
        "key": "MeterValueSampleInterval",
        "readonly": false,
        "value": 30
      },
      {
        "key": "SupportedFeatureProfiles",
        "readonly": true,
        "value": "Core,LocalAuthListManagement"
      },
      {
        "key": "LocalAuthListEnabled",
        "readonly": false,
        "value": false
      },
      {
        "key": "AuthorizeRemoteTxRequests",
        "readonly": false,
        "value": false
      }
    ]
  },
  "AutomaticTransactionGenerator": {
    "enable": true,
    "minDuration": 60,
    "maxDuration": 80,
    "minDelayBetweenTwoTransactions": 15,
    "maxDelayBetweenTwoTransactions": 30,
    "probabilityOfStart": 1,
    "stopAfterHours": 0.3,
    "stopOnConnectionFailure": false
  },
  "Connectors": {
    "0": {},
    "1": {
      "bootStatus": "Available",
      "MeterValues": [
        {
          "unit": "Percent",
          "context": "Sample.Periodic",
          "measurand": "SoC",
          "location": "EV"
        },
        {
          "unit": "Wh",
          "context": "Sample.Periodic"
        }
      ]
    },
    "2": {
      "bootStatus": "Preparing",
      "MeterValues": [
        {
          "unit": "Percent",
          "context": "Sample.Periodic",
          "measurand": "SoC",
          "location": "EV"
        },
        {
          "unit": "Wh",
          "context": "Sample.Periodic"
        }
      ]
    },
    "3": {
      "bootStatus": "Faulted",
      "MeterValues": [
        {
          "unit": "Percent",
          "context": "Sample.Periodic",
          "measurand": "SoC",
          "location": "EV"
        },
        {
          "unit": "Wh",
          "context": "Sample.Periodic"
        }
      ]
    }
  }
}
